{
  "received_at": "2026-04-14 11:11:25",
  "status": "ALINDI",
  "source": "fatura_erp_prediction",
  "payload": {
    "fatura_no": "TAHMIN-20260330113143-43",
    "cari_kod": "C004",
    "firma_adi": "E TEKNOLOJİ",
    "tarih": "2026-03-31",
    "kalemler": [
      {
        "stok_kod": "STK-0201",
        "urun_adi": "Mouse",
        "miktar": 15.0,
        "birim_fiyat": 2426.67,
        "kdv_orani": 20.0
      }
    ],
    "ara_toplam": 36400.05,
    "genel_toplam": 43680.060000000005
  }
}